<Properties GitUserInfo="UsingGIT" StartupConfiguration="{A7F075D4-256A-433B-952A-E01BCF6C34AE}|Default">
  <MonoDevelop.Ide.Workbench>
    <Files>
      <File FileName="Duplicates_Multithreading/Program.cs" Line="18" Column="47" />
      <File FileName="../PhoneBook/PhoneBook/Program.cs" />
    </Files>
    <Pads>
      <Pad Id="ProjectPad">
        <State name="__root__">
          <Node name="Duplicates_Multithreading" expanded="True">
            <Node name="Duplicates_Multithreading" expanded="True">
              <Node name="Program.cs" selected="True" />
            </Node>
          </Node>
        </State>
      </Pad>
    </Pads>
  </MonoDevelop.Ide.Workbench>
  <MonoDevelop.Ide.DebuggingService.PinnedWatches />
  <MonoDevelop.Ide.Workspace ActiveConfiguration="Debug" />
  <MonoDevelop.Ide.DebuggingService.Breakpoints>
    <BreakpointStore />
  </MonoDevelop.Ide.DebuggingService.Breakpoints>
  <MultiItemStartupConfigurations />
  <MonoDevelop.Ide.ItemProperties.Duplicates__Multithreading PreferredExecutionTarget="MonoDevelop.Default" />
</Properties>